setup.cfg
setup.py
controlcore/__init__.py
controlcore/config.py
controlcore/consumer.py
controlcore/publisher.py
controlcore.egg-info/PKG-INFO
controlcore.egg-info/SOURCES.txt
controlcore.egg-info/dependency_links.txt
controlcore.egg-info/requires.txt
controlcore.egg-info/top_level.txt