Metadata-Version: 1.0
Name: controlcore
Version: 0.0.3
Summary: Underground Laboratory Control Core
Home-page: https://gitlab.com/cup-ibs/controlcore
Author: Hyounggyu Kim
Author-email: hgkim10@gmail.com
License: GPL
Platform: UNKNOWN
